Hyvebrain/__init__.py
hyvebrain-1.0.6.dist-info/LICENCE
hyvebrain-1.0.6.dist-info/METADATA
hyvebrain-1.0.6.dist-info/WHEEL
hyvebrain-1.0.6.dist-info/top_level.txt
hyvebrain-1.0.6.dist-info/RECORD
