Metadata-Version: 2.1
Name: hyvebrain
Version: 1.0.6
Summary: Hyvebrain API Client Library
Home-page: https://hyvebrain.com/
Author: Tegan Burns
Author-email: python@hyvebrain.com
License: UNKNOWN
Platform: UNKNOWN
